simple_tracker_redis/__init__.py
simple_tracker_redis/tracker.py
simple_tracker_redis-0.1.4.dist-info/METADATA
simple_tracker_redis-0.1.4.dist-info/WHEEL
simple_tracker_redis-0.1.4.dist-info/top_level.txt
simple_tracker_redis-0.1.4.dist-info/RECORD
