Metadata-Version: 2.4
Name: simple-tracker-redis
Version: 0.1.4
Summary: Simple Item Count Tracker Using Redis
Requires-Python: >=3.8
Requires-Dist: redis>=6.1.1
